{"season": "2022", "round": "9", "url": "https://en.wikipedia.org/wiki/2022_Canadian_Grand_Prix", "raceName": "Canadian Grand Prix", "Circuit": {"circuitId": "villeneuve", "url": "https://en.wikipedia.org/wiki/Circuit_Gilles_Villeneuve", "circuitName": "Circuit Gilles Villeneuve", "Location": {"lat": "45.5", "long": "-73.5228", "locality": "Montreal", "country": "Canada"}}, "date": "2022-06-19", "time": "18:00:00Z", "Laps": [{"number": "1", "Timings": [{"driverId": "max_verstappen", "time": "1:23.396", "position": "1"}, {"driverId": "alonso", "time": "1:24.435", "position": "2"}, {"driverId": "sainz", "time": "1:25.160", "position": "3"}, {"driverId": "hamilton", "time": "1:26.209", "position": "4"}, {"driverId": "kevin_magnussen", "time": "1:27.088", "position": "5"}, {"driverId": "ocon", "time": "1:27.881", "position": "6"}, {"driverId": "russell", "time": "1:28.761", "position": "7"}, {"driverId": "mick_schumacher", "time": "1:29.342", "position": "8"}, {"driverId": "ricciardo", "time": "1:29.928", "position": "9"}, {"driverId": "zhou", "time": "1:30.286", "position": "10"}, {"driverId": "perez", "time": "1:31.210", "position": "11"}, {"driverId": "albon", "time": "1:31.675", "position": "12"}, {"driverId": "bottas", "time": "1:31.719", "position": "13"}, {"driverId": "norris", "time": "1:32.333", "position": "14"}, {"driverId": "vettel", "time": "1:32.647", "position": "15"}, {"driverId": "stroll", "time": "1:33.179", "position": "16"}, {"driverId": "gasly", "time": "1:33.394", "position": "17"}, {"driverId": "leclerc", "time": "1:33.701", "position": "18"}, {"driverId": "tsunoda", "time": "1:34.569", "position": "19"}, {"driverId": "latifi", "time": "1:35.457", "position": "20"}]}, {"number": "2", "Timings": [{"driverId": "max_verstappen", "time": "1:18.960", "position": "1"}, {"driverId": "alonso", "time": "1:19.603", "position": "2"}, {"driverId": "sainz", "time": "1:19.339", "position": "3"}, {"driverId": "hamilton", "time": "1:19.549", "position": "4"}, {"driverId": "kevin_magnussen", "time": "1:20.105", "position": "5"}, {"driverId": "ocon", "time": "1:20.334", "position": "6"}, {"driverId": "russell", "time": "1:20.352", "position": "7"}, {"driverId": "mick_schumacher", "time": "1:20.785", "position": "8"}, {"driverId": "ricciardo", "time": "1:21.014", "position": "9"}, {"driverId": "zhou", "time": "1:21.166", "position": "10"}, {"driverId": "perez", "time": "1:21.239", "position": "11"}, {"driverId": "albon", "time": "1:21.297", "position": "12"}, {"driverId": "bottas", "time": "1:21.920", "position": "13"}, {"driverId": "norris", "time": "1:22.278", "position": "14"}, {"driverId": "vettel", "time": "1:22.343", "position": "15"}, {"driverId": "stroll", "time": "1:22.423", "position": "16"}, {"driverId": "leclerc", "time": "1:22.270", "position": "17"}, {"driverId": "gasly", "time": "1:23.231", "position": "18"}, {"driverId": "tsunoda", "time": "1:22.382", "position": "19"}, {"driverId": "latifi", "time": "1:22.432", "position": "20"}]}, {"number": "3", "Timings": [{"driverId": "max_verstappen", "time": "1:18.818", "position": "1"}, {"driverId": "sainz", "time": "1:19.147", "position": "2"}, {"driverId": "alonso", "time": "1:20.136", "position": "3"}, {"driverId": "hamilton", "time": "1:19.013", "position": "4"}, {"driverId": "kevin_magnussen", "time": "1:19.833", "position": "5"}, {"driverId": "russell", "time": "1:19.238", "position": "6"}, {"driverId": "ocon", "time": "1:20.692", "position": "7"}, {"driverId": "mick_schumacher", "time": "1:19.589", "position": "8"}, {"driverId": "ricciardo", "time": "1:19.773", "position": "9"}, {"driverId": "zhou", "time": "1:19.583", "position": "10"}, {"driverId": "perez", "time": "1:19.654", "position": "11"}, {"driverId": "albon", "time": "1:20.304", "position": "12"}, {"driverId": "bottas", "time": "1:20.082", "position": "13"}, {"driverId": "norris", "time": "1:19.980", "position": "14"}, {"driverId": "vettel", "time": "1:20.173", "position": "15"}, {"driverId": "leclerc", "time": "1:20.117", "position": "16"}, {"driverId": "stroll", "time": "1:20.762", "position": "17"}, {"driverId": "gasly", "time": "1:20.406", "position": "18"}, {"driverId": "tsunoda", "time": "1:20.513", "position": "19"}, {"driverId": "latifi", "time": "1:21.123", "position": "20"}]}, {"number": "4", "Timings": [{"driverId": "max_verstappen", "time": "1:18.393", "position": "1"}, {"driverId": "sainz", "time": "1:19.086", "position": "2"}, {"driverId": "alonso", "time": "1:18.980", "position": "3"}, {"driverId": "hamilton", "time": "1:19.158", "position": "4"}, {"driverId": "kevin_magnussen", "time": "1:19.729", "position": "5"}, {"driverId": "russell", "time": "1:19.154", "position": "6"}, {"driverId": "ocon", "time": "1:19.474", "position": "7"}, {"driverId": "mick_schumacher", "time": "1:19.195", "position": "8"}, {"driverId": "zhou", "time": "1:19.457", "position": "9"}, {"driverId": "ricciardo", "time": "1:20.389", "position": "10"}, {"driverId": "perez", "time": "1:19.428", "position": "11"}, {"driverId": "albon", "time": "1:19.484", "position": "12"}, {"driverId": "bottas", "time": "1:19.433", "position": "13"}, {"driverId": "norris", "time": "1:19.663", "position": "14"}, {"driverId": "vettel", "time": "1:19.529", "position": "15"}, {"driverId": "leclerc", "time": "1:19.397", "position": "16"}, {"driverId": "stroll", "time": "1:20.067", "position": "17"}, {"driverId": "gasly", "time": "1:20.010", "position": "18"}, {"driverId": "tsunoda", "time": "1:20.110", "position": "19"}, {"driverId": "latifi", "time": "1:20.610", "position": "20"}]}, {"number": "5", "Timings": [{"driverId": "max_verstappen", "time": "1:18.293", "position": "1"}, {"driverId": "sainz", "time": "1:18.214", "position": "2"}, {"driverId": "alonso", "time": "1:18.455", "position": "3"}, {"driverId": "hamilton", "time": "1:18.660", "position": "4"}, {"driverId": "russell", "time": "1:18.867", "position": "5"}, {"driverId": "kevin_magnussen", "time": "1:20.233", "position": "6"}, {"driverId": "ocon", "time": "1:19.384", "position": "7"}, {"driverId": "mick_schumacher", "time": "1:20.064", "position": "8"}, {"driverId": "zhou", "time": "1:19.573", "position": "9"}, {"driverId": "ricciardo", "time": "1:19.655", "position": "10"}, {"driverId": "perez", "time": "1:19.787", "position": "11"}, {"driverId": "albon", "time": "1:19.690", "position": "12"}, {"driverId": "bottas", "time": "1:19.942", "position": "13"}, {"driverId": "norris", "time": "1:19.602", "position": "14"}, {"driverId": "leclerc", "time": "1:19.294", "position": "15"}, {"driverId": "stroll", "time": "1:19.595", "position": "16"}, {"driverId": "tsunoda", "time": "1:20.065", "position": "17"}, {"driverId": "latifi", "time": "1:20.483", "position": "18"}, {"driverId": "vettel", "time": "1:35.658", "position": "19"}, {"driverId": "gasly", "time": "1:35.629", "position": "20"}]}]}